paper_solver/__init__.py
paper_solver/_canonical_constraint.py
paper_solver/_constraints.py
paper_solver/_esolve.py
paper_solver/_minimize_constrained.py
paper_solver/_numdiff.py
paper_solver/_large_scale_constrained/__init__.py
paper_solver/_large_scale_constrained/equality_constrained_sqp.py
paper_solver/_large_scale_constrained/projections.py
paper_solver/_large_scale_constrained/qp_subproblem.py
paper_solver/_large_scale_constrained/setup.py
paper_solver/_large_scale_constrained/tr_interior_point.py
paper_solver/_large_scale_constrained/tests/__init__.py
paper_solver/_large_scale_constrained/tests/test_projections.py
paper_solver/_large_scale_constrained/tests/test_qp_subproblem.py
paper_solver-0.1.0.dist-info/licenses/LICENSE
paper_solver-0.1.0.dist-info/METADATA
paper_solver-0.1.0.dist-info/WHEEL
paper_solver-0.1.0.dist-info/top_level.txt
paper_solver-0.1.0.dist-info/RECORD
