Metadata-Version: 2.4
Name: paper-solver
Version: 0.1.0
Summary: 一个专门面向造纸行业的高性能约束优化求解器
Home-page: https://github.com/baijifei/paper-solver
Author: QC Lab
Author-email: Your Name <your.email@example.com>
License: Apache License
Classifier: Development Status :: 3 - Alpha
Classifier: Intended Audience :: Science/Research
Classifier: License :: OSI Approved :: Apache Software License
Classifier: Operating System :: OS Independent
Classifier: Programming Language :: Python :: 3
Classifier: Programming Language :: Python :: 3.7
Classifier: Programming Language :: Python :: 3.8
Classifier: Programming Language :: Python :: 3.9
Classifier: Programming Language :: Python :: 3.10
Classifier: Topic :: Scientific/Engineering :: Mathematics
Classifier: Topic :: Scientific/Engineering
Requires-Python: >=3.7
License-File: LICENSE
Requires-Dist: numpy>=1.17.0
Requires-Dist: scipy>=1.5.0
Requires-Dist: autograd>=1.3
Provides-Extra: sparse
Requires-Dist: scikit-sparse>=0.4.5; extra == "sparse"
Provides-Extra: dev
Requires-Dist: pytest>=6.0; extra == "dev"
Requires-Dist: pytest-cov>=2.0; extra == "dev"
Requires-Dist: black>=22.0; extra == "dev"
Requires-Dist: isort>=5.0; extra == "dev"
Requires-Dist: mypy>=0.900; extra == "dev"
Dynamic: author
Dynamic: home-page
Dynamic: license-file
Dynamic: requires-python
